{
  "project_info": {
    "project_number": "724920391446",
    "project_id": "whatsapp-555b7",
    "storage_bucket": "whatsapp-555b7.appspot.com"
  },
  "client": [
    {
      "client_info": {
        "mobilesdk_app_id": "1:724920391446:android:b1c650cc3cea9a11a8e237",
        "android_client_info": {
          "package_name": "com.example.whatsapp"
        }
      },
      "oauth_client": [
        {
          "client_id": "724920391446-4k291ikqn4rj1leca41klvn8pbh7kmm2.apps.googleusercontent.com",
          "client_type": 3
        }
      ],
      "api_key": [
        {
          "current_key": "AIzaSyDiYzxF0Fm-ipvjJhi_hst1RdRcp5skNGo"
        }
      ],
      "services": {
        "appinvite_service": {
          "other_platform_oauth_client": [
            {
              "client_id": "724920391446-4k291ikqn4rj1leca41klvn8pbh7kmm2.apps.googleusercontent.com",
              "client_type": 3
            }
          ]
        }
      }
    }
  ],
  "configuration_version": "1"
}